minto/__init__.py
minto/exception.py
minto/experiment.py
minto/table.py
minto/utils.py
minto/migrator/__init__.py
minto/migrator/v0tov1.py
minto/problems/__init__.py
minto/problems/cvrp.py
minto/problems/knapsack.py
minto/problems/problem.py
minto/problems/tsp.py
minto/v0/__init__.py
minto/v0/typing.py
minto/v0/consts/__init__.py
minto/v0/consts/default.py
minto/v0/exceptions/__init__.py
minto/v0/exceptions/exceptions.py
minto/v0/experiment/__init__.py
minto/v0/experiment/experiment.py
minto/v0/io/__init__.py
minto/v0/io/load.py
minto/v0/io/save.py
minto/v0/records/__init__.py
minto/v0/records/records.py
minto/v0/records/sampleset_expansion.py
minto/v0/table/__init__.py
minto/v0/table/table.py
minto/v1/__init__.py
minto/v1/datastore.py
minto/v1/exceptions.py
minto/v1/exp_dataspace.py
minto/v1/json_encoder.py
minto-1.3.0.dist-info/licenses/LICENSE
minto-1.3.0.dist-info/METADATA
minto-1.3.0.dist-info/WHEEL
minto-1.3.0.dist-info/top_level.txt
minto-1.3.0.dist-info/RECORD
